{"v":4,"entries":{"atomic-accordion--docs":{"id":"atomic-accordion--docs","title":"atomic/Accordion","name":"Docs","importPath":"./src/atomic/Accordion/Accordion.stories.tsx","type":"docs","tags":["docs","autodocs"],"storiesImports":[]},"atomic-accordion--primary":{"type":"story","id":"atomic-accordion--primary","name":"Primary","title":"atomic/Accordion","importPath":"./src/atomic/Accordion/Accordion.stories.tsx","tags":["story"]},"atomic-button--docs":{"id":"atomic-button--docs","title":"atomic/Button","name":"Docs","importPath":"./src/atomic/Button/Button.stories.tsx","type":"docs","tags":["docs","autodocs"],"storiesImports":[]},"atomic-button--primary":{"type":"story","id":"atomic-button--primary","name":"Primary","title":"atomic/Button","importPath":"./src/atomic/Button/Button.stories.tsx","tags":["story"]},"atomic-button--secondary":{"type":"story","id":"atomic-button--secondary","name":"Secondary","title":"atomic/Button","importPath":"./src/atomic/Button/Button.stories.tsx","tags":["story"]},"atomic-button--tertiary":{"type":"story","id":"atomic-button--tertiary","name":"Tertiary","title":"atomic/Button","importPath":"./src/atomic/Button/Button.stories.tsx","tags":["story"]},"atomic-button--educator":{"type":"story","id":"atomic-button--educator","name":"Educator","title":"atomic/Button","importPath":"./src/atomic/Button/Button.stories.tsx","tags":["story"]},"atomic-button--with-icon":{"type":"story","id":"atomic-button--with-icon","name":"With Icon","title":"atomic/Button","importPath":"./src/atomic/Button/Button.stories.tsx","tags":["story"]},"atomic-buttonish--docs":{"id":"atomic-buttonish--docs","title":"atomic/Buttonish","name":"Docs","importPath":"./src/atomic/Buttonish/Buttonish.stories.tsx","type":"docs","tags":["docs","autodocs"],"storiesImports":[]},"atomic-buttonish--external-link":{"type":"story","id":"atomic-buttonish--external-link","name":"External Link","title":"atomic/Buttonish","importPath":"./src/atomic/Buttonish/Buttonish.stories.tsx","tags":["story"]},"atomic-buttonish--internal-link":{"type":"story","id":"atomic-buttonish--internal-link","name":"Internal Link","title":"atomic/Buttonish","importPath":"./src/atomic/Buttonish/Buttonish.stories.tsx","tags":["story"]},"atomic-circularloader--docs":{"id":"atomic-circularloader--docs","title":"atomic/CircularLoader","name":"Docs","importPath":"./src/atomic/CircularLoader/CircularLoader.stories.tsx","type":"docs","tags":["docs","autodocs"],"storiesImports":[]},"atomic-circularloader--primary":{"type":"story","id":"atomic-circularloader--primary","name":"Primary","title":"atomic/CircularLoader","importPath":"./src/atomic/CircularLoader/CircularLoader.stories.tsx","tags":["story"]},"atomic-colorswatch--docs":{"id":"atomic-colorswatch--docs","title":"atomic/ColorSwatch","name":"Docs","importPath":"./src/atomic/ColorSwatch/ColorSwatch.stories.tsx","type":"docs","tags":["docs","autodocs"],"storiesImports":[]},"atomic-colorswatch--primary":{"type":"story","id":"atomic-colorswatch--primary","name":"Primary","title":"atomic/ColorSwatch","importPath":"./src/atomic/ColorSwatch/ColorSwatch.stories.tsx","tags":["story"]},"atomic-expandtoggle--docs":{"id":"atomic-expandtoggle--docs","title":"atomic/ExpandToggle","name":"Docs","importPath":"./src/atomic/ExpandToggle/ExpandToggle.stories.tsx","type":"docs","tags":["docs","autodocs"],"storiesImports":[]},"atomic-expandtoggle--primary":{"type":"story","id":"atomic-expandtoggle--primary","name":"Primary","title":"atomic/ExpandToggle","importPath":"./src/atomic/ExpandToggle/ExpandToggle.stories.tsx","tags":["story"]},"atomic-externallink--docs":{"id":"atomic-externallink--docs","title":"atomic/ExternalLink","name":"Docs","importPath":"./src/atomic/ExternalLink/ExternalLink.stories.tsx","type":"docs","tags":["docs","autodocs"],"storiesImports":[]},"atomic-externallink--primary":{"type":"story","id":"atomic-externallink--primary","name":"Primary","title":"atomic/ExternalLink","importPath":"./src/atomic/ExternalLink/ExternalLink.stories.tsx","tags":["story"]},"atomic-figure--docs":{"id":"atomic-figure--docs","title":"atomic/Figure","name":"Docs","importPath":"./src/atomic/Figure/Figure.stories.tsx","type":"docs","tags":["docs","autodocs"],"storiesImports":[]},"atomic-figure--vertical-layout":{"type":"story","id":"atomic-figure--vertical-layout","name":"Vertical Layout","title":"atomic/Figure","importPath":"./src/atomic/Figure/Figure.stories.tsx","tags":["story"]},"atomic-figure--horizontal-layout":{"type":"story","id":"atomic-figure--horizontal-layout","name":"Horizontal Layout","title":"atomic/Figure","importPath":"./src/atomic/Figure/Figure.stories.tsx","tags":["story"]},"atomic-figure--with-background":{"type":"story","id":"atomic-figure--with-background","name":"With Background","title":"atomic/Figure","importPath":"./src/atomic/Figure/Figure.stories.tsx","tags":["story"]},"atomic-image--docs":{"id":"atomic-image--docs","title":"atomic/Image","name":"Docs","importPath":"./src/atomic/Image/Image.stories.tsx","type":"docs","tags":["docs","autodocs"],"storiesImports":[]},"atomic-image--primary":{"type":"story","id":"atomic-image--primary","name":"Primary","title":"atomic/Image","importPath":"./src/atomic/Image/Image.stories.tsx","tags":["story"]},"atomic-link--docs":{"id":"atomic-link--docs","title":"atomic/Link","name":"Docs","importPath":"./src/atomic/Link/Link.stories.tsx","type":"docs","tags":["docs","autodocs"],"storiesImports":[]},"atomic-link--primary":{"type":"story","id":"atomic-link--primary","name":"Primary","title":"atomic/Link","importPath":"./src/atomic/Link/Link.stories.tsx","tags":["story"]},"atomic-mixedlink--docs":{"id":"atomic-mixedlink--docs","title":"atomic/MixedLink","name":"Docs","importPath":"./src/atomic/MixedLink/MixedLink.stories.tsx","type":"docs","tags":["docs","autodocs"],"storiesImports":[]},"atomic-mixedlink--external-link":{"type":"story","id":"atomic-mixedlink--external-link","name":"External Link","title":"atomic/MixedLink","importPath":"./src/atomic/MixedLink/MixedLink.stories.tsx","tags":["story"]},"atomic-mixedlink--internal-link":{"type":"story","id":"atomic-mixedlink--internal-link","name":"Internal Link","title":"atomic/MixedLink","importPath":"./src/atomic/MixedLink/MixedLink.stories.tsx","tags":["story"]},"atomic-progress-bar-progressbar--docs":{"id":"atomic-progress-bar-progressbar--docs","title":"atomic/Progress/Bar/ProgressBar","name":"Docs","importPath":"./src/atomic/Progress/Bar/ProgressBar.stories.tsx","type":"docs","tags":["docs","autodocs"],"storiesImports":[]},"atomic-progress-bar-progressbar--primary":{"type":"story","id":"atomic-progress-bar-progressbar--primary","name":"Primary","title":"atomic/Progress/Bar/ProgressBar","importPath":"./src/atomic/Progress/Bar/ProgressBar.stories.tsx","tags":["story"]},"atomic-progress-radial-progressradial--docs":{"id":"atomic-progress-radial-progressradial--docs","title":"atomic/Progress/Radial/ProgressRadial","name":"Docs","importPath":"./src/atomic/Progress/Radial/ProgressRadial.stories.tsx","type":"docs","tags":["docs","autodocs"],"storiesImports":[]},"atomic-progress-radial-progressradial--primary":{"type":"story","id":"atomic-progress-radial-progressradial--primary","name":"Primary","title":"atomic/Progress/Radial/ProgressRadial","importPath":"./src/atomic/Progress/Radial/ProgressRadial.stories.tsx","tags":["story"]},"atomic-responsiveimage--docs":{"id":"atomic-responsiveimage--docs","title":"atomic/ResponsiveImage","name":"Docs","importPath":"./src/atomic/ResponsiveImage/ResponsiveImage.stories.tsx","type":"docs","tags":["docs","autodocs"],"storiesImports":[]},"atomic-responsiveimage--primary":{"type":"story","id":"atomic-responsiveimage--primary","name":"Primary","title":"atomic/ResponsiveImage","importPath":"./src/atomic/ResponsiveImage/ResponsiveImage.stories.tsx","tags":["story"]},"atomic-share-copyurlbutton--docs":{"id":"atomic-share-copyurlbutton--docs","title":"atomic/Share/CopyUrlButton","name":"Docs","importPath":"./src/atomic/Share/CopyUrlButton.stories.tsx","type":"docs","tags":["docs","autodocs"],"storiesImports":[]},"atomic-share-copyurlbutton--primary":{"type":"story","id":"atomic-share-copyurlbutton--primary","name":"Primary","title":"atomic/Share/CopyUrlButton","importPath":"./src/atomic/Share/CopyUrlButton.stories.tsx","tags":["story"]},"atomic-share-emailbutton--docs":{"id":"atomic-share-emailbutton--docs","title":"atomic/Share/EmailButton","name":"Docs","importPath":"./src/atomic/Share/EmailButton.stories.tsx","type":"docs","tags":["docs","autodocs"],"storiesImports":[]},"atomic-share-emailbutton--primary":{"type":"story","id":"atomic-share-emailbutton--primary","name":"Primary","title":"atomic/Share/EmailButton","importPath":"./src/atomic/Share/EmailButton.stories.tsx","tags":["story"]},"atomic-share-facebookbutton--docs":{"id":"atomic-share-facebookbutton--docs","title":"atomic/Share/FacebookButton","name":"Docs","importPath":"./src/atomic/Share/FacebookButton.stories.tsx","type":"docs","tags":["docs","autodocs"],"storiesImports":[]},"atomic-share-facebookbutton--primary":{"type":"story","id":"atomic-share-facebookbutton--primary","name":"Primary","title":"atomic/Share/FacebookButton","importPath":"./src/atomic/Share/FacebookButton.stories.tsx","tags":["story"]},"atomic-share-twitterbutton--docs":{"id":"atomic-share-twitterbutton--docs","title":"atomic/Share/TwitterButton","name":"Docs","importPath":"./src/atomic/Share/TwitterButton.stories.tsx","type":"docs","tags":["docs","autodocs"],"storiesImports":[]},"atomic-share-twitterbutton--primary":{"type":"story","id":"atomic-share-twitterbutton--primary","name":"Primary","title":"atomic/Share/TwitterButton","importPath":"./src/atomic/Share/TwitterButton.stories.tsx","tags":["story"]},"atomic-slideout--docs":{"id":"atomic-slideout--docs","title":"atomic/Slideout","name":"Docs","importPath":"./src/atomic/Slideout/Slideout.stories.tsx","type":"docs","tags":["docs","autodocs"],"storiesImports":[]},"atomic-slideout--primary":{"type":"story","id":"atomic-slideout--primary","name":"Primary","title":"atomic/Slideout","importPath":"./src/atomic/Slideout/Slideout.stories.tsx","tags":["story"]},"atomic-toast--docs":{"id":"atomic-toast--docs","title":"atomic/Toast","name":"Docs","importPath":"./src/atomic/Toast/Toast.stories.tsx","type":"docs","tags":["docs","autodocs"],"storiesImports":[]},"atomic-toast--primary":{"type":"story","id":"atomic-toast--primary","name":"Primary","title":"atomic/Toast","importPath":"./src/atomic/Toast/Toast.stories.tsx","tags":["story"]},"atomic-video-patterns-generic--docs":{"id":"atomic-video-patterns-generic--docs","title":"atomic/Video/patterns/Generic","name":"Docs","importPath":"./src/atomic/Video/patterns/Generic/Generic.stories.tsx","type":"docs","tags":["docs","autodocs"],"storiesImports":[]},"atomic-video-patterns-generic--primary":{"type":"story","id":"atomic-video-patterns-generic--primary","name":"Primary","title":"atomic/Video/patterns/Generic","importPath":"./src/atomic/Video/patterns/Generic/Generic.stories.tsx","tags":["story"]},"atomic-video-patterns-youtube--docs":{"id":"atomic-video-patterns-youtube--docs","title":"atomic/Video/patterns/YouTube","name":"Docs","importPath":"./src/atomic/Video/patterns/YouTube/YouTube.stories.tsx","type":"docs","tags":["docs","autodocs"],"storiesImports":[]},"atomic-video-patterns-youtube--primary":{"type":"story","id":"atomic-video-patterns-youtube--primary","name":"Primary","title":"atomic/Video/patterns/YouTube","importPath":"./src/atomic/Video/patterns/YouTube/YouTube.stories.tsx","tags":["story"]},"content-blocks-complextable--docs":{"id":"content-blocks-complextable--docs","title":"content-blocks/ComplexTable","name":"Docs","importPath":"./src/content-blocks/ComplexTable/ComplexTable.stories.tsx","type":"docs","tags":["docs","autodocs"],"storiesImports":[]},"content-blocks-complextable--primary":{"type":"story","id":"content-blocks-complextable--primary","name":"Primary","title":"content-blocks/ComplexTable","importPath":"./src/content-blocks/ComplexTable/ComplexTable.stories.tsx","tags":["story"]},"content-blocks-complextable--secondary":{"type":"story","id":"content-blocks-complextable--secondary","name":"Secondary","title":"content-blocks/ComplexTable","importPath":"./src/content-blocks/ComplexTable/ComplexTable.stories.tsx","tags":["story"]},"content-blocks-complextable--child":{"type":"story","id":"content-blocks-complextable--child","name":"Child","title":"content-blocks/ComplexTable","importPath":"./src/content-blocks/ComplexTable/ComplexTable.stories.tsx","tags":["story"]},"content-blocks-simpletable--docs":{"id":"content-blocks-simpletable--docs","title":"content-blocks/SimpleTable","name":"Docs","importPath":"./src/content-blocks/SimpleTable/SimpleTable.stories.tsx","type":"docs","tags":["docs","autodocs"],"storiesImports":[]},"content-blocks-simpletable--primary":{"type":"story","id":"content-blocks-simpletable--primary","name":"Primary","title":"content-blocks/SimpleTable","importPath":"./src/content-blocks/SimpleTable/SimpleTable.stories.tsx","tags":["story"]},"form-error--docs":{"id":"form-error--docs","title":"form/Error","name":"Docs","importPath":"./src/form/Error/Error.stories.tsx","type":"docs","tags":["docs","autodocs"],"storiesImports":[]},"form-error--primary":{"type":"story","id":"form-error--primary","name":"Primary","title":"form/Error","importPath":"./src/form/Error/Error.stories.tsx","tags":["story"]},"form-formbuttons--docs":{"id":"form-formbuttons--docs","title":"form/FormButtons","name":"Docs","importPath":"./src/form/FormButtons/FormButtons.stories.tsx","type":"docs","tags":["docs","autodocs"],"storiesImports":[]},"form-formbuttons--primary":{"type":"story","id":"form-formbuttons--primary","name":"Primary","title":"form/FormButtons","importPath":"./src/form/FormButtons/FormButtons.stories.tsx","tags":["story"]},"form-formfield--docs":{"id":"form-formfield--docs","title":"form/FormField","name":"Docs","importPath":"./src/form/FormField/FormField.stories.tsx","type":"docs","tags":["docs","autodocs"],"storiesImports":[]},"form-formfield--text-field":{"type":"story","id":"form-formfield--text-field","name":"Text Field","title":"form/FormField","importPath":"./src/form/FormField/FormField.stories.tsx","tags":["story"]},"form-formfield--password-field":{"type":"story","id":"form-formfield--password-field","name":"Password Field","title":"form/FormField","importPath":"./src/form/FormField/FormField.stories.tsx","tags":["story"]},"form-formfield--with-error":{"type":"story","id":"form-formfield--with-error","name":"With Error","title":"form/FormField","importPath":"./src/form/FormField/FormField.stories.tsx","tags":["story"]},"form-horizontalslider--docs":{"id":"form-horizontalslider--docs","title":"form/HorizontalSlider","name":"Docs","importPath":"./src/form/HorizontalSlider/HorizontalSlider.stories.tsx","type":"docs","tags":["docs","autodocs"],"storiesImports":[]},"form-horizontalslider--single-handle":{"type":"story","id":"form-horizontalslider--single-handle","name":"Single Handle","title":"form/HorizontalSlider","importPath":"./src/form/HorizontalSlider/HorizontalSlider.stories.tsx","tags":["story"]},"form-horizontalslider--double-handle":{"type":"story","id":"form-horizontalslider--double-handle","name":"Double Handle","title":"form/HorizontalSlider","importPath":"./src/form/HorizontalSlider/HorizontalSlider.stories.tsx","tags":["story"]},"form-horizontalslider--disabled":{"type":"story","id":"form-horizontalslider--disabled","name":"Disabled","title":"form/HorizontalSlider","importPath":"./src/form/HorizontalSlider/HorizontalSlider.stories.tsx","tags":["story"]},"form-input--docs":{"id":"form-input--docs","title":"form/Input","name":"Docs","importPath":"./src/form/Input/Input.stories.tsx","type":"docs","tags":["docs","autodocs"],"storiesImports":[]},"form-input--primary":{"type":"story","id":"form-input--primary","name":"Primary","title":"form/Input","importPath":"./src/form/Input/Input.stories.tsx","tags":["story"]},"form-input-patterns-password--docs":{"id":"form-input-patterns-password--docs","title":"form/Input/patterns/Password","name":"Docs","importPath":"./src/form/Input/patterns/Password/Password.stories.tsx","type":"docs","tags":["docs","autodocs"],"storiesImports":[]},"form-input-patterns-password--primary":{"type":"story","id":"form-input-patterns-password--primary","name":"Primary","title":"form/Input/patterns/Password","importPath":"./src/form/Input/patterns/Password/Password.stories.tsx","tags":["story"]},"form-select--docs":{"id":"form-select--docs","title":"form/Select","name":"Docs","importPath":"./src/form/Select/Select.stories.tsx","type":"docs","tags":["docs","autodocs"],"storiesImports":[]},"form-select--primary":{"type":"story","id":"form-select--primary","name":"Primary","title":"form/Select","importPath":"./src/form/Select/Select.stories.tsx","tags":["story"]},"form-select--with-option-groups":{"type":"story","id":"form-select--with-option-groups","name":"With Option Groups","title":"form/Select","importPath":"./src/form/Select/Select.stories.tsx","tags":["story"]},"form-select--with-empty-option":{"type":"story","id":"form-select--with-empty-option","name":"With Empty Option","title":"form/Select","importPath":"./src/form/Select/Select.stories.tsx","tags":["story"]},"form-selectlistbox--docs":{"id":"form-selectlistbox--docs","title":"form/SelectListbox","name":"Docs","importPath":"./src/form/SelectListbox/SelectListbox.stories.tsx","type":"docs","tags":["docs","autodocs"],"storiesImports":[]},"form-selectlistbox--primary":{"type":"story","id":"form-selectlistbox--primary","name":"Primary","title":"form/SelectListbox","importPath":"./src/form/SelectListbox/SelectListbox.stories.tsx","tags":["story"]},"form-selectlistbox--multi-select":{"type":"story","id":"form-selectlistbox--multi-select","name":"Multi Select","title":"form/SelectListbox","importPath":"./src/form/SelectListbox/SelectListbox.stories.tsx","tags":["story"]},"form-switch--docs":{"id":"form-switch--docs","title":"form/Switch","name":"Docs","importPath":"./src/form/Switch/Switch.stories.tsx","type":"docs","tags":["docs","autodocs"],"storiesImports":[]},"form-switch--primary":{"type":"story","id":"form-switch--primary","name":"Primary","title":"form/Switch","importPath":"./src/form/Switch/Switch.stories.tsx","tags":["story"]},"layout-basicmodal--docs":{"id":"layout-basicmodal--docs","title":"layout/BasicModal","name":"Docs","importPath":"./src/layout/BasicModal/BasicModal.stories.tsx","type":"docs","tags":["docs","autodocs"],"storiesImports":[]},"layout-basicmodal--primary":{"type":"story","id":"layout-basicmodal--primary","name":"Primary","title":"layout/BasicModal","importPath":"./src/layout/BasicModal/BasicModal.stories.tsx","tags":["story"]},"layout-basicmodal--dark-mode":{"type":"story","id":"layout-basicmodal--dark-mode","name":"Dark Mode","title":"layout/BasicModal","importPath":"./src/layout/BasicModal/BasicModal.stories.tsx","tags":["story"]},"layout-carousel--docs":{"id":"layout-carousel--docs","title":"layout/Carousel","name":"Docs","importPath":"./src/layout/Carousel/Carousel.stories.tsx","type":"docs","tags":["docs","autodocs"],"storiesImports":[]},"layout-carousel--primary":{"type":"story","id":"layout-carousel--primary","name":"Primary","title":"layout/Carousel","importPath":"./src/layout/Carousel/Carousel.stories.tsx","tags":["story"]},"layout-columns--docs":{"id":"layout-columns--docs","title":"layout/Columns","name":"Docs","importPath":"./src/layout/Columns/Columns.stories.tsx","type":"docs","tags":["docs","autodocs"],"storiesImports":[]},"layout-columns--primary":{"type":"story","id":"layout-columns--primary","name":"Primary","title":"layout/Columns","importPath":"./src/layout/Columns/Columns.stories.tsx","tags":["story"]},"layout-container--docs":{"id":"layout-container--docs","title":"layout/Container","name":"Docs","importPath":"./src/layout/Container/Container.stories.tsx","type":"docs","tags":["docs","autodocs"],"storiesImports":[]},"layout-container--primary":{"type":"story","id":"layout-container--primary","name":"Primary","title":"layout/Container","importPath":"./src/layout/Container/Container.stories.tsx","tags":["story"]},"layout-container--nested":{"type":"story","id":"layout-container--nested","name":"Nested","title":"layout/Container","importPath":"./src/layout/Container/Container.stories.tsx","tags":["story"]},"layout-grid--docs":{"id":"layout-grid--docs","title":"layout/Grid","name":"Docs","importPath":"./src/layout/Grid/Grid.stories.tsx","type":"docs","tags":["docs","autodocs"],"storiesImports":[]},"layout-grid--primary":{"type":"story","id":"layout-grid--primary","name":"Primary","title":"layout/Grid","importPath":"./src/layout/Grid/Grid.stories.tsx","tags":["story"]},"layout-grid--with-feature":{"type":"story","id":"layout-grid--with-feature","name":"With Feature","title":"layout/Grid","importPath":"./src/layout/Grid/Grid.stories.tsx","tags":["story"]},"layout-masonrygrid--docs":{"id":"layout-masonrygrid--docs","title":"layout/MasonryGrid","name":"Docs","importPath":"./src/layout/MasonryGrid/MasonryGrid.stories.tsx","type":"docs","tags":["docs","autodocs"],"storiesImports":[]},"layout-masonrygrid--primary":{"type":"story","id":"layout-masonrygrid--primary","name":"Primary","title":"layout/MasonryGrid","importPath":"./src/layout/MasonryGrid/MasonryGrid.stories.tsx","tags":["story"]},"layout-masonrygrid--randomized":{"type":"story","id":"layout-masonrygrid--randomized","name":"Randomized","title":"layout/MasonryGrid","importPath":"./src/layout/MasonryGrid/MasonryGrid.stories.tsx","tags":["story"]},"layout-slideoutmenu--docs":{"id":"layout-slideoutmenu--docs","title":"layout/SlideoutMenu","name":"Docs","importPath":"./src/layout/SlideoutMenu/SlideoutMenu.stories.tsx","type":"docs","tags":["docs","autodocs"],"storiesImports":[]},"layout-slideoutmenu--primary":{"type":"story","id":"layout-slideoutmenu--primary","name":"Primary","title":"layout/SlideoutMenu","importPath":"./src/layout/SlideoutMenu/SlideoutMenu.stories.tsx","tags":["story"]},"svg-iconcomposer--docs":{"id":"svg-iconcomposer--docs","title":"svg/IconComposer","name":"Docs","importPath":"./src/svg/IconComposer/IconComposer.stories.tsx","type":"docs","tags":["docs","autodocs"],"storiesImports":[]},"svg-iconcomposer--playground":{"type":"story","id":"svg-iconcomposer--playground","name":"Playground","title":"svg/IconComposer","importPath":"./src/svg/IconComposer/IconComposer.stories.tsx","tags":["story"]},"svg-iconcomposer--all-icons":{"type":"story","id":"svg-iconcomposer--all-icons","name":"All Icons","title":"svg/IconComposer","importPath":"./src/svg/IconComposer/IconComposer.stories.tsx","tags":["story"]}}}
