{
  "color": {
    "primary": {
      "gray_pale": {
        "value": "{color.neutral.04}",
        "attributes": {
          "category": "color"
        }
      },
      "charcoal": {
        "value": "{color.neutral.80}",
        "attributes": {
          "category": "color"
        }
      },
      "teal": {
        "value": "{color.teal.72}",
        "attributes": {
          "category": "color"
        }
      },
      "turquoise": {
        "value": "{color.turquoise.63}",
        "attributes": {
          "category": "color"
        }
      }
    },
    "complementary": {
      "gray_light": {
        "value": "{color.neutral.12}",
        "attributes": {
          "category": "color"
        }
      },
      "gray": {
        "value": "{color.neutral.58}",
        "attributes": {
          "category": "color"
        }
      },
      "black": {
        "value": "{color.neutral.87}",
        "attributes": {
          "category": "color"
        }
      },
      "teal_pale": {
        "value": "{color.teal.09}",
        "attributes": {
          "category": "color"
        }
      },
      "turquoise_light": {
        "value": "{color.turquoise.18}",
        "attributes": {
          "category": "color"
        }
      },
      "teal_light": {
        "value": "{color.teal.68}",
        "attributes": {
          "category": "color"
        }
      },
      "teal_dark": {
        "value": "{color.teal.83}",
        "attributes": {
          "category": "color"
        }
      }
    },
    "accent": {
      "orange": "{color.orange.31}",
      "attributes": {
        "category": "color"
      }
    }
  }
}
